addon_utils/__init__.pyi
addon_utils/py.typed
animsys_refactor/__init__.pyi
animsys_refactor/py.typed
aud/__init__.pyi
aud/py.typed
bge/__init__.pyi
bge/py.typed
bge/app/__init__.pyi
bge/constraints/__init__.pyi
bge/types/__init__.pyi
bgl/__init__.pyi
bgl/py.typed
bl_i18n_utils/__init__.pyi
bl_i18n_utils/py.typed
bl_i18n_utils/bl_extract_messages/__init__.pyi
bl_i18n_utils/merge_po/__init__.pyi
bl_i18n_utils/settings/__init__.pyi
bl_i18n_utils/utils/__init__.pyi
bl_i18n_utils/utils_languages_menu/__init__.pyi
bl_i18n_utils/utils_rtl/__init__.pyi
bl_operators/__init__.pyi
bl_operators/py.typed
bl_operators/add_mesh_torus/__init__.pyi
bl_operators/anim/__init__.pyi
bl_operators/bmesh/__init__.pyi
bl_operators/bmesh/find_adjacent/__init__.pyi
bl_operators/clip/__init__.pyi
bl_operators/console/__init__.pyi
bl_operators/file/__init__.pyi
bl_operators/freestyle/__init__.pyi
bl_operators/image/__init__.pyi
bl_operators/mask/__init__.pyi
bl_operators/mesh/__init__.pyi
bl_operators/node/__init__.pyi
bl_operators/object/__init__.pyi
bl_operators/object_align/__init__.pyi
bl_operators/object_quick_effects/__init__.pyi
bl_operators/object_randomize_transform/__init__.pyi
bl_operators/presets/__init__.pyi
bl_operators/rigidbody/__init__.pyi
bl_operators/screen_play_rendered_anim/__init__.pyi
bl_operators/sequencer/__init__.pyi
bl_operators/uvcalc_follow_active/__init__.pyi
bl_operators/uvcalc_lightmap/__init__.pyi
bl_operators/uvcalc_smart_project/__init__.pyi
bl_operators/vertexpaint_dirt/__init__.pyi
bl_operators/view3d/__init__.pyi
bl_operators/wm/__init__.pyi
bl_previews_utils/__init__.pyi
bl_previews_utils/py.typed
bl_previews_utils/bl_previews_render/__init__.pyi
bl_ui/__init__.pyi
bl_ui/py.typed
bl_ui/properties_animviz/__init__.pyi
bl_ui/properties_constraint/__init__.pyi
bl_ui/properties_data_armature/__init__.pyi
bl_ui/properties_data_bone/__init__.pyi
bl_ui/properties_data_camera/__init__.pyi
bl_ui/properties_data_curve/__init__.pyi
fake_bpy_module_2.78-20250130.dist-info/METADATA
fake_bpy_module_2.78-20250130.dist-info/WHEEL
fake_bpy_module_2.78-20250130.dist-info/top_level.txt
fake_bpy_module_2.78-20250130.dist-info/RECORD
